{"Version":"1.0.0.0","LastState":11,"Modules":[{"ModuleName":"Front Left","ModuleId":0,"Encoder":{"Id":3,"Name":"FL_CanCoder","Model":"CANCoder vers. H","CANbus":"269F66F1463847532020204B18300DFF","CANbusFriendly":"CANIVORE","SelectedMotorType":null,"IsStandaloneFx":false},"SteerMotor":{"Id":2,"Name":"FL_Steer","Model":"Talon FX vers. C","CANbus":"269F66F1463847532020204B18300DFF","CANbusFriendly":"CANIVORE","SelectedMotorType":{"Name":"WCP Kraken x60","FreeSpeedRps":96.7,"SlipCurrentLimit":120,"StatorCurrentLimit":60},"IsStandaloneFx":false},"DriveMotor":{"Id":1,"Name":"FL_Drive","Model":"Talon FX vers. C","CANbus":"269F66F1463847532020204B18300DFF","CANbusFriendly":"CANIVORE","SelectedMotorType":{"Name":"WCP Kraken x60","FreeSpeedRps":96.7,"SlipCurrentLimit":120,"StatorCurrentLimit":60},"IsStandaloneFx":false},"IsEncoderInverted":false,"IsSteerInverted":true,"SelectedEncoderType":"CANcoder","EncoderOffset":0.128173828125,"DriveMotorSelectionState":1,"SteerMotorSelectionState":1,"SteerEncoderSelectionState":1,"IsModuleValidationComplete":true,"ValidatedSteerId":2,"ValidatedDriveId":1,"ValidatedEncoderId":3},{"ModuleName":"Front Right","ModuleId":1,"Encoder":{"Id":6,"Name":"FR_CanCoder","Model":"CANCoder vers. H","CANbus":"269F66F1463847532020204B18300DFF","CANbusFriendly":"CANIVORE","SelectedMotorType":null,"IsStandaloneFx":false},"SteerMotor":{"Id":5,"Name":"FR_Steer","Model":"Talon FX vers. C","CANbus":"269F66F1463847532020204B18300DFF","CANbusFriendly":"CANIVORE","SelectedMotorType":{"Name":"WCP Kraken x60","FreeSpeedRps":96.7,"SlipCurrentLimit":120,"StatorCurrentLimit":60},"IsStandaloneFx":false},"DriveMotor":{"Id":4,"Name":"FR_Drive","Model":"Talon FX vers. C","CANbus":"269F66F1463847532020204B18300DFF","CANbusFriendly":"CANIVORE","SelectedMotorType":{"Name":"WCP Kraken x60","FreeSpeedRps":96.7,"SlipCurrentLimit":120,"StatorCurrentLimit":60},"IsStandaloneFx":false},"IsEncoderInverted":false,"IsSteerInverted":true,"SelectedEncoderType":"CANcoder","EncoderOffset":0.103271484375,"DriveMotorSelectionState":1,"SteerMotorSelectionState":1,"SteerEncoderSelectionState":1,"IsModuleValidationComplete":true,"ValidatedSteerId":5,"ValidatedDriveId":4,"ValidatedEncoderId":6},{"ModuleName":"Back Left","ModuleId":2,"Encoder":{"Id":13,"Name":"BL_CanCoder","Model":"CANCoder","CANbus":"269F66F1463847532020204B18300DFF","CANbusFriendly":"CANIVORE","SelectedMotorType":null,"IsStandaloneFx":false},"SteerMotor":{"Id":12,"Name":"BL_Steer","Model":"Talon FX vers. C","CANbus":"269F66F1463847532020204B18300DFF","CANbusFriendly":"CANIVORE","SelectedMotorType":{"Name":"WCP Kraken x60","FreeSpeedRps":96.7,"SlipCurrentLimit":120,"StatorCurrentLimit":60},"IsStandaloneFx":false},"DriveMotor":{"Id":11,"Name":"BL_Drive","Model":"Talon FX vers. C","CANbus":"269F66F1463847532020204B18300DFF","CANbusFriendly":"CANIVORE","SelectedMotorType":{"Name":"WCP Kraken x60","FreeSpeedRps":96.7,"SlipCurrentLimit":120,"StatorCurrentLimit":60},"IsStandaloneFx":false},"IsEncoderInverted":false,"IsSteerInverted":true,"SelectedEncoderType":"CANcoder","EncoderOffset":-0.36279296875,"DriveMotorSelectionState":1,"SteerMotorSelectionState":1,"SteerEncoderSelectionState":1,"IsModuleValidationComplete":true,"ValidatedSteerId":12,"ValidatedDriveId":11,"ValidatedEncoderId":13},{"ModuleName":"Back Right","ModuleId":3,"Encoder":{"Id":16,"Name":"BR_CanCoder","Model":"CANCoder vers. H","CANbus":"269F66F1463847532020204B18300DFF","CANbusFriendly":"CANIVORE","SelectedMotorType":null,"IsStandaloneFx":false},"SteerMotor":{"Id":15,"Name":"BR_Steer","Model":"Talon FX vers. C","CANbus":"269F66F1463847532020204B18300DFF","CANbusFriendly":"CANIVORE","SelectedMotorType":{"Name":"WCP Kraken x60","FreeSpeedRps":96.7,"SlipCurrentLimit":120,"StatorCurrentLimit":60},"IsStandaloneFx":false},"DriveMotor":{"Id":14,"Name":"BR_Drive","Model":"Talon FX vers. C","CANbus":"269F66F1463847532020204B18300DFF","CANbusFriendly":"CANIVORE","SelectedMotorType":{"Name":"WCP Kraken x60","FreeSpeedRps":96.7,"SlipCurrentLimit":120,"StatorCurrentLimit":60},"IsStandaloneFx":false},"IsEncoderInverted":false,"IsSteerInverted":true,"SelectedEncoderType":"CANcoder","EncoderOffset":0.38232421875,"DriveMotorSelectionState":1,"SteerMotorSelectionState":1,"SteerEncoderSelectionState":1,"IsModuleValidationComplete":true,"ValidatedSteerId":15,"ValidatedDriveId":14,"ValidatedEncoderId":16}],"SwerveOptions":{"kSpeedAt12Volts":5.771943462685408,"Gyro":{"Id":10,"Name":"DT_Pigeon","Model":"Pigeon 2 vers. S","CANbus":"269F66F1463847532020204B18300DFF","CANbusFriendly":"CANIVORE","SelectedMotorType":null,"IsStandaloneFx":false},"IsValidGyroCANbus":true,"VerticalTrackSizeInches":22.75,"HorizontalTrackSizeInches":22.75,"WheelRadiusInches":1.9375,"IsLeftSideInverted":false,"IsRightSideInverted":true,"SwerveModuleType":5,"SwerveModuleConfiguration":{"ModuleBrand":5,"DriveRatio":5.357142857142857,"SteerRatio":18.75,"CouplingRatio":3.125,"CustomName":"L3+"},"HasVerifiedSteer":true,"SelectedModuleManufacturer":"Swerve Drive Specialties (SDS)","HasVerifiedDrive":true,"IsValidConfiguration":true}}